pyclickupy/__init__.py
pyclickupy/client.py
pyclickupy/exceptions.py
pyclickupy/models.py
pyclickupy/helpers/__init__.py
pyclickupy/helpers/formatting.py
pyclickupy/helpers/timefuncs.py
pyclickupy-0.2.2.dist-info/METADATA
pyclickupy-0.2.2.dist-info/WHEEL
pyclickupy-0.2.2.dist-info/RECORD
