Metadata-Version: 2.4
Name: pyclickupy
Version: 0.2.2
Summary: Python SDK for the ClickUp API
Requires-Dist: pendulum
Requires-Dist: pydantic
Requires-Dist: requests
Requires-Dist: timefhuman
Requires-Dist: word2number
Provides-Extra: test
Requires-Dist: pytest-cov>=4.1.0; extra == 'test'
Requires-Dist: pytest>=7.4.0; extra == 'test'
